<?xml version="1.0" encoding="UTF-8"?>
<iniciativa_completa>
  <legislatura>VIII</legislatura>
  <numero_diario>557</numero_diario>
  <tipo_sesion>ordinaria</tipo_sesion>
  <organo>Comisión de Igualdad y Bienestar Social</organo>
  <presidente>Ilma. Sra. Dña. María Eulalia Quevedo Ariza</presidente>
  <numero_sesion />
  <fecha>
    <dia>19</dia>
    <mes>octubre</mes>
    <anio>2011</anio>
  </fecha>
  <tipo_epigrafe>Preguntas orales</tipo_epigrafe>
  <iniciativa>
    <tipo_iniciativa>Preguntas orales</tipo_iniciativa>
    <materias>Persona jubilada, Anciano, Ayuda social, Política social, Prestación social</materias>
    <numero_expediente>8-10/POC-000807</numero_expediente>
    <extracto>8-10/POC-000807. Pregunta oral relativa al documento Andalucía Junta Sesenta y cinco (pág. 17).</extracto>
    <proponentes>los Ilmos. Sres. Dña. Verónica Pérez Fernández y D. Ramón Díaz Alcaraz, del G.P. Socialista.</proponentes>
    <intervienen>D. Ramón Díaz Alcaraz, del G.P. Socialista. Dña. Micaela Navarro Garzón, Consejera para la Igualdad y Bienestar Social.</intervienen>
    <intervencion>
      <interviniente>La señora QUEVEDO ARIZA, PRESIDENTA DE LA COMISIÓN</interviniente>
      <discurso>
        <parrafo>—Gracias, señora Consejera.</parrafo>
        <parrafo>Pasamos a la siguiente pregunta con ruego de respuesta oral en comisión, a propuesta del Grupo Socialista, referente al documento Andalucía Junta Sesenta y cinco. Para ello tiene la palabra el señor Díaz Alcaraz.</parrafo>
      </discurso>
    </intervencion>
    <intervencion>
      <interviniente>El señor DÍAZ ALCARAZ</interviniente>
      <discurso>
        <parrafo>—Muchas gracias, señora Presidenta. Señora Consejera.</parrafo>
        <parrafo>El Grupo Socialista trae esta pregunta a la Comisión de Igualdad con el objetivo fundamental de conocer los contenidos y las personas afectadas por un instrumento puesto en funcionamiento por su consejería, como es la Tarjeta Andalucía Junta Sesenta y cinco.</parrafo>
        <parrafo>Hace escasos segundos hablaba usted de invertir en lo que es la educación, invertir en el futuro de los jóvenes; también invertir en nuestros mayores. Son muchos los andaluces y andaluzas que, ya en un periodo de su vida que han superado los 65 años, ven cómo iniciativas como esta, como la Tarjeta 65, que se pone a su disposición desde la Consejería para la Igualdad, pues les facilita determinados servicios y prestaciones que, a esa edad, donde ya no tiene uno la misma agilidad mental ni la misma fuerza física que cuando se es más joven, pues facilita de una forma tremenda cualquier trámite, incluso el abaratamiento de algunos servicios y de algunas prestaciones.</parrafo>
        <parrafo>Señora Consejera, su consejería, que ha sido punta de lanza, a lo largo de estos últimos años, en poner en marcha y poner en práctica medidas sociales, quizás pioneras en el Estado español, pone nuevamente al servicio de los ciudadanos, de los andaluces y de las andaluzas, la tarjeta para mayores de 65 años. Esta tarjeta, que se puso en funcionamiento por un real decreto del año 2001, ha sufrido ya un largo periodo, a través del cual se ha ido mejorando y han ido aumentando todas las prestaciones a que el poseedor de la misma se le da derecho.</parrafo>
        <parrafo>Nuestros mayores, los mayores de 65 años, a los que va dirigida esta tarjeta, verdadero patrimonio de nuestra comunidad autónoma que con su enorme esfuerzo han hecho posible que hoy tengamos esta Andalucía actual, se merecen no solamente esta herramienta, sino cualquier otra iniciativa que desde la Consejería para la Igualdad y Bienestar Social y desde el Gobierno de la Junta de Andalucía podamos poner a su disposición.</parrafo>
        <parrafo>Por todo ello, señora Consejera, desde el Grupo Socialista nos gustaría conocer un poco más en profundidad cuántos andaluces y andaluzas se benefician de este instrumento, cuántos lo han solicitado, y también qué prestaciones y modalidades conlleva el ser poseedor de este documento.</parrafo>
        <parrafo>Muchas gracias, señora Presidenta.</parrafo>
      </discurso>
    </intervencion>
    <intervencion>
      <interviniente>La señora QUEVEDO ARIZA, PRESIDENTA DE LA COMISIÓN</interviniente>
      <discurso>
        <parrafo>—Gracias, señor Díaz Alcaraz.</parrafo>
        <parrafo>Tiene la palabra la señora Consejera.</parrafo>
      </discurso>
    </intervencion>
    <intervencion>
      <interviniente>La señora NAVARRO GARZÓN, CONSEJERA PARA LA IGUALDAD Y BIENESTAR SOCIAL</interviniente>
      <discurso>
        <parrafo>—Gracias, señora Presidenta. Señor Díaz.</parrafo>
        <parrafo>Es posible invertir en educación, y, por lo tanto, invertir en futuro, gracias a la renuncia y el esfuerzo que hicieron los mayores, a los que nos vamos a referir ahora. Por eso, entiendo que tiene que seguir siendo prioritario atender las necesidades que ellos tienen en este momento. Y no solo las necesidades de ser atendidos por una política social o por una política asistencial, que también en aquellos casos que la necesiten, sino también de poner a su disposición todo aquello que sea posible que les permita recuperar una parte de esas asignaturas pendientes que tienen, que han tenido, a lo largo de su vida, porque tuvieron que dedicarse a generar riqueza para que nuestra tierra fuera la que es hoy.</parrafo>
        <parrafo>Andalucía fue la primera comunidad autónoma que dispuso de una tarjeta gratuita para personas mayores de 65 años, la Tarjeta Andalucía Junta Sesenta y cinco. Después de dos lustros de existencia, la tarjeta se ha convertido en un documento de referencia que es utilizado por casi un millón de personas mayores, más del 80% de las personas mayores de 65 años que hay en Andalucía, que son un millón doscientas mil. Mediante el acceso a las ventajas que proporciona el uso de la tarjeta, las personas mayores titulares de la tarjeta se han ahorrado 162 millones de euros desde el año 2001, gracias, entre otras cosas, a los descuentos obtenidos, por ejemplo, en el Servicio de Teleasistencia, en los desplazamientos interurbanos realizados por Andalucía, en comidas en los centros de día, en la compra de gafas, monturas y cristales, y en adaptación de prótesis auditivas. Es un dinero que, evidentemente, digo, se han ahorrado, no han tenido que pagar de su bolsillo, aunque, en algunos casos, cuando no tenemos que pagarlos en ese momento, no somos conscientes del coste que eso significa.</parrafo>
        <parrafo>Gracias a la tarjeta, las personas mayores disfrutan del Servicio Andaluz de Teleasistencia, con un descuento que va del 40%, al 80% y hasta del cien por cien. Para muchas de estas personas mayores a partir de los 80 años y aquellas personas que tienen la tarjeta oro el servicio es totalmente gratuito.</parrafo>
        <parrafo>El Servicio Andaluz de Teleasistencia, como recurso social, goza de gran aceptación y valoración entre las personas usuarias, y también entre los familiares y personas cuidadoras de personas dependientes, porque garantiza una tranquilidad y una seguridad que les proporciona el sentirse acompañadas. En la actualidad cuenta con más de ciento sesenta y seis mil personas usuarias, el Servicio de Teleasistencia, y, de estas, ciento dos mil son personas mayores titulares de la Tarjeta Andalucía Junta Sesenta y cinco. Gracias a esta tarjeta, sus titulares pueden realizar desplazamientos interurbanos por Andalucía, dentro de Andalucía, con un descuento en el precio del billete del 50%. Tan sencillo como introducir la Tarjeta Andalucía Junta Sesenta y cinco en las máquinas lectoras de tarjetas instaladas en los autobuses y puntos de venta de las empresas de transportes que hayan suscrito este convenio con la Agencia de Servicios Sociales y de Dependencia para que se puedan beneficiar del 50% de descuento.</parrafo>
        <parrafo>Actualmente existen 74 empresas de transporte adheridas en toda Andalucía con descuento garantizado que ofertan más de mil destinos interurbanos a mitad de precio en toda Andalucía, cinco millones setecientos mil viajes durante el años 2010.</parrafo>
        <parrafo>Aquí se nota también el cambio de perfil. Se nota que las personas que hoy se jubilan, que hoy cumplen 65 años, sus condiciones de vida, sus expectativas, sus inquietudes culturales y de todo tipo son totalmente distintas, y, evidentemente, eso se nota también en otras actividades y tiene que ver, de manera muy directa también, con los desplazamientos.</parrafo>
        <parrafo>Otra de las ventajas de la tarjeta son los descuentos en la adquisición de gafas y audífonos, que son del 30% hasta el 55%, en el primer caso, y del 30% al 35% para los audífonos. En la actualidad hay 858 centros ópticos, y 180 para el caso de audífonos, que están adheridos a este programa en toda Andalucía, y en los que han obtenido descuentos veintitrés mil personas mayores.</parrafo>
        <parrafo>El planteamiento de nuevos modelos de vida, en los que hay cabida para el ocio, el descanso, el deporte, las actividades creativas, y el fomento de las relaciones sociales, proyectó una línea de actuación más relacionada con lo que hoy denominamos «envejecimiento activo y saludable», y, además, está perfectamente relacionado. Cuanta más actividad, más salud integral tiene una persona mayor. Poco a poco, sus primeros resultados en el programa de empresas colaboradoras, a través del cual, y sobre la base de convenios suscritos con distintas entidades, se ofrece una serie de ventajas a las personas titulares de la tarjeta, todas ellas identificadas por su carácter heterogéneo.</parrafo>
        <parrafo>Actualmente se han firmado convenios con 105 entidades, las cuales ponen a disposición de las personas titulares de la tarjeta 452 establecimientos donde acudir y obtener descuentos y disfrutar de múltiples descuentos en hoteles, cines, encuentros deportivos, monumentos, parques temáticos, o en el acceso a nuevas tecnologías, entre otros, el acceso gratuito al servicio de orientación jurídica. A través de este programa también se recibe este asesoramiento jurídico en temas relacionados con su vida diaria, y lo hacen profesionales de los colegios oficiales de abogados de Andalucía.</parrafo>
        <parrafo>El poder acceder al servicio de comedor en los centros de día de la Junta de Andalucía, con un 50% del precio del menú en el caso de tener la modalidad oro... Sabe que hay dos modalidades de tarjeta: la verde y la oro. Pero aquí, al revés que en la realidad cotidiana, tiene la oro quien tiene menos ingresos. Normalmente, en una entidad bancaria le dan la tarjeta oro a quien tiene muchos ingresos. En este caso, es al revés: la tarjeta verde la tiene quien tiene más ingresos, y la tarjeta oro la tiene la persona que tiene menos ingresos, porque tener la tarjeta oro significa tener más descuentos y más posibilidades, o incluso la gratuidad total de los servicios que utiliza.</parrafo>
        <parrafo>Un programa, el programa de comedor, del que se han beneficiado, en el año 2010, 10.900 personas mayores en Andalucía.</parrafo>
        <parrafo>Solicitar una subvención para la adecuación funcional de la vivienda —el programa de ascensores, por ejemplo—, o la adecuación de cuartos de baño, que tiene la propia Consejería de Obras Públicas...</parrafo>
      </discurso>
    </intervencion>
    <intervencion>
      <interviniente>La señora QUEVEDO ARIZA, PRESIDENTA DE LA COMISIÓN</interviniente>
      <discurso>
        <parrafo>—Señora Consejera, vaya terminando.</parrafo>
      </discurso>
    </intervencion>
    <intervencion>
      <interviniente>La señora NAVARRO GARZÓN, CONSEJERA PARA LA IGUALDAD Y BIENESTAR SOCIAL</interviniente>
      <discurso>
        <parrafo>—Termino enseguida, señora Presidenta.</parrafo>
        <parrafo>… es otra de las posibilidades a las que tienen acceso directo las personas que tienen la tarjeta.</parrafo>
        <parrafo>Repito, en un 92,99% de las personas encuestadas manifiestan tener una impresión buena, o muy buena, de los servicios que les ha ofrecido la tarjeta.</parrafo>
        <parrafo>Muchas gracias.</parrafo>
      </discurso>
    </intervencion>
    <intervencion>
      <interviniente>La señora QUEVEDO ARIZA, PRESIDENTA DE LA COMISIÓN</interviniente>
      <discurso>
        <parrafo>—Gracias, señora Consejera.</parrafo>
        <parrafo>Tiene la palabra el señor Díaz Alcaraz.</parrafo>
      </discurso>
    </intervencion>
    <intervencion>
      <interviniente>El señor DÍAZ ALCARAZ</interviniente>
      <discurso>
        <parrafo>—Muchas gracias, señora Presidenta.</parrafo>
        <parrafo>Señora Consejera, en primer lugar, agradecerle la información que nos acaba de trasladar, y decir que lo que usted nos acaba de explicar ahora mismo viene a corroborar lo que es una política, por parte del Gobierno socialista, de atención no solamente —como decíamos antes— a invertir en Educación, sino también a invertir en ese patrimonio que son nuestros mayores, a los cuales, cualquier cosa que hagamos por ellos, yo creo que nunca estará suficientemente agradecido por lo que ellos le han dado a esta tierra hasta ponerla en el lugar en el que hoy está.</parrafo>
        <parrafo>Por lo tanto, señora Consejera, yo le agradezco enormemente su información, y le animo a que siga usted, que ya lleva muchísimo tiempo en el ámbito de las políticas sociales y se ha convertido en un referente en nuestro país de lo que ha sido innovar y facilitarle no solamente a los mayores, sino en todo el ámbito de las políticas sociales..., a que siga en la misma línea y siga trabajando en ese sentido, que sin duda los ciudadanos y las ciudadanas andaluzas se lo van a agradecer muy mucho.</parrafo>
        <parrafo>Muchísimas gracias, señora Presidenta.</parrafo>
      </discurso>
    </intervencion>
    <intervencion>
      <interviniente>La señora QUEVEDO ARIZA, PRESIDENTA DE LA COMISIÓN</interviniente>
      <discurso>
        <parrafo>—Gracias, señor Díaz Alcaraz.</parrafo>
        <parrafo>Tiene la consejera diez segundos.</parrafo>
      </discurso>
    </intervencion>
    <intervencion>
      <interviniente>La señora NAVARRO GARZÓN, CONSEJERA PARA LA IGUALDAD Y BIENESTAR SOCIAL</interviniente>
      <discurso>
        <parrafo>—Por pura cortesía, para decirle que también, en ese sentido, se nota cómo se está recuperando el tiempo perdido. Por ejemplo, el 57% de las personas que hacen uso de este recurso son mujeres, o que más utilizan la tarjeta son mujeres, y el 43% varones. Yo creo que ahí también las mujeres han decidido recuperar el tiempo perdido.</parrafo>
      </discurso>
    </intervencion>
  </iniciativa>
</iniciativa_completa>

